{
  "lastUpdated": "2026-03-16T23:36:57.250Z",
  "articles": [
    {
      "id": "7fm5rg",
      "type": "news",
      "headline": "Nvidia unveils AI computing module for space-based data centers",
      "blurb": "Chipmaker says new system is designed for satellites and other power-constrained missions The post Nvidia unveils AI computing module for space-based data centers appeared first on SpaceNews.",
      "takeaway": "Aerospace developments expand industry horizons.",
      "source": {
        "name": "SpaceNews",
        "url": "https://spacenews.com/nvidia-unveils-ai-computing-module-for-space-based-data-centers/"
      },
      "category": "aerospace",
      "keywords": [
        "space"
      ],
      "publishedAt": "2026-03-16T22:17:41.000Z"
    },
    {
      "id": "du72jt",
      "type": "news",
      "headline": "How Much Do Airbus A380 Pilots Make In 2026?",
      "blurb": "Explore the engineering and operational complexity of the A380, and how these factors contribute to some of the highest pilot salaries in aviation.",
      "takeaway": "Airbus activity reflects European aerospace trends.",
      "source": {
        "name": "Simple Flying",
        "url": "https://simpleflying.com/how-much-do-airbus-a380-pilots-make-in-2026/"
      },
      "category": "commercial",
      "keywords": [
        "airbus",
        "pilot"
      ],
      "publishedAt": "2026-03-16T22:00:17.000Z"
    },
    {
      "id": "9illcm",
      "type": "news",
      "headline": "Kayrros sale signals rising demand for satellite intelligence amid Hormuz crisis",
      "blurb": "Tensions around the Strait of Hormuz have pushed interest in commercial geospatial intelligence services to unprecedented levels, an executive at Kayrros said after the satellite analytics provider agreed to be acquired by Energy Aspects. The post Kayrros sale signals rising demand for satellite ...",
      "takeaway": "Aerospace developments expand industry horizons.",
      "source": {
        "name": "SpaceNews",
        "url": "https://spacenews.com/kayrros-sale-signals-rising-demand-for-satellite-intelligence-amid-hormuz-crisis/"
      },
      "category": "aerospace",
      "keywords": [
        "space"
      ],
      "publishedAt": "2026-03-16T21:47:33.000Z"
    },
    {
      "id": "wp6zqt",
      "type": "news",
      "headline": "Is Austin About To Land Its First Nonstop Flights To Asia?",
      "blurb": "Austin already has Europe. Now Seoul is emerging as its most intriguing long-haul target.",
      "takeaway": "Commercial aviation dynamics shape travel industry.",
      "source": {
        "name": "Simple Flying",
        "url": "https://simpleflying.com/is-austin-about-to-land-its-first-nonstop-flights-to-asia/"
      },
      "category": "commercial",
      "keywords": [],
      "publishedAt": "2026-03-16T21:37:12.000Z"
    },
    {
      "id": "8tx4rw",
      "type": "news",
      "headline": "Is A Boeing 787-9 Bigger Than An Airbus A330-900neo?",
      "blurb": "Two top widebodies go toe-to-toe.",
      "takeaway": "Boeing developments impact global aviation supply chain.",
      "source": {
        "name": "Simple Flying",
        "url": "https://simpleflying.com/boeing-787-9-bigger-airbus-a330-900neo/"
      },
      "category": "commercial",
      "keywords": [
        "boeing",
        "airbus"
      ],
      "publishedAt": "2026-03-16T21:00:17.000Z"
    },
    {
      "id": "pai-assess-safety-risk",
      "type": "pai-blog",
      "headline": "How to Assess Safety Risk",
      "blurb": "A practical walkthrough of safety risk assessment under 14 CFR Part 5.",
      "takeaway": "Safety implications warrant industry attention.",
      "source": {
        "name": "PAI Consulting — SMS Quick Takes",
        "url": "https://www.paiconsulting.com/sms-quick-takes-all-about-sms/how-to-assess-safety-risk"
      },
      "category": "safety",
      "keywords": [
        "sms",
        "risk assessment",
        "faa",
        "part 5"
      ],
      "publishedAt": "2026-03-16T23:36:53.600Z",
      "paiContent": true
    },
    {
      "id": "ezzgoi",
      "type": "news",
      "headline": "Israel says it destroyed Airbus A340-300 used by Iran’s late leader",
      "blurb": "Israel said it destroyed an aircraft used by Iran’s late Supreme Leader, Ayatollah Ali Khamenei, in an overnight… The post Israel says it destroyed Airbus A340-300 used by Iran’s late leader appeared first on AeroTime.",
      "takeaway": "Airbus activity reflects European aerospace trends.",
      "source": {
        "name": "AeroTime Hub",
        "url": "https://www.aerotime.aero/articles/israel-destroys-iran-government-airbus-a340"
      },
      "category": "commercial",
      "keywords": [
        "airbus"
      ],
      "publishedAt": "2026-03-16T20:40:23.000Z"
    },
    {
      "id": "jse0xy",
      "type": "news",
      "headline": "Will Boom Ever Fly? United CEO Gives Overture A 50-50 Chance",
      "blurb": "Scott Kirby has some strong thoughts on the startup program and manufacturer.",
      "takeaway": "Commercial aviation dynamics shape travel industry.",
      "source": {
        "name": "Simple Flying",
        "url": "https://simpleflying.com/will-boom-ever-fly-united-ceo-overture-50-50-chance/"
      },
      "category": "commercial",
      "keywords": [],
      "publishedAt": "2026-03-16T20:30:17.000Z"
    },
    {
      "id": "l0swit",
      "type": "news",
      "headline": "The Airlines With The World's Most Innovative First Class Suites In 2026",
      "blurb": "These airlines offer some of the world’s most innovative first class suites, turning long-haul flights into private, luxury experiences in the sky.",
      "takeaway": "Commercial aviation dynamics shape travel industry.",
      "source": {
        "name": "Simple Flying",
        "url": "https://simpleflying.com/airlines-worlds-most-innovative-first-class-suites-2026/"
      },
      "category": "commercial",
      "keywords": [
        "airline"
      ],
      "publishedAt": "2026-03-16T20:00:17.000Z"
    },
    {
      "id": "bibzzv",
      "type": "news",
      "headline": "Florida Lawmakers Target ADS-B Use For Landing Fees",
      "blurb": "Bill would restrict airports from using aircraft ADS-B data to determine landing fees.",
      "takeaway": "Commercial aviation dynamics shape travel industry.",
      "source": {
        "name": "AVweb",
        "url": "https://avweb.com/aviation-news/aviation-law/florida-targets-ads-b-landing-fees/"
      },
      "category": "general-aviation",
      "keywords": [
        "airport"
      ],
      "publishedAt": "2026-03-16T19:55:39.000Z"
    },
    {
      "id": "pai-safety-culture",
      "type": "pai-blog",
      "headline": "Safety Culture in Aviation SMS",
      "blurb": "How organizational culture shapes safety outcomes and what it takes to build a reporting culture that supports SMS.",
      "takeaway": "Safety implications warrant industry attention.",
      "source": {
        "name": "PAI Consulting — SMS Quick Takes",
        "url": "https://www.paiconsulting.com/sms-quick-takes-all-about-sms/safety-culture-in-aviation-sms"
      },
      "category": "safety",
      "keywords": [
        "sms",
        "safety culture",
        "reporting",
        "just culture"
      ],
      "publishedAt": "2026-03-16T23:36:53.600Z",
      "paiContent": true
    },
    {
      "id": "2sb4qd",
      "type": "news",
      "headline": "NASA Invites Media to Learn About Upcoming X-59 Test Flights",
      "blurb": "NASA will hold a media teleconference at 5:30 p.m. EDT on Thursday, March 19 to highlight plans for its X-59 quiet supersonic aircraft’s upcoming flight tests. The teleconference is set to take place after the X-59 is scheduled to complete its second flight, in California. For the media call, NAS...",
      "takeaway": "Aerospace developments expand industry horizons.",
      "source": {
        "name": "NASA",
        "url": "https://www.nasa.gov/news-release/nasa-invites-media-to-learn-about-upcoming-x-59-test-flights/"
      },
      "category": "aerospace",
      "keywords": [
        "nasa"
      ],
      "publishedAt": "2026-03-16T19:48:16.000Z"
    },
    {
      "id": "vlnjb2",
      "type": "news",
      "headline": "Vietnam warns of flight cuts as jet fuel squeeze tied to Iran war deepens",
      "blurb": "Vietnam’s aviation industry is bracing for potential flight cuts beginning in April 2026 after China and Thailand halted exports… The post Vietnam warns of flight cuts as jet fuel squeeze tied to Iran war deepens appeared first on AeroTime.",
      "takeaway": "Commercial aviation dynamics shape travel industry.",
      "source": {
        "name": "AeroTime Hub",
        "url": "https://www.aerotime.aero/articles/vietnam-flight-cuts-jet-fuel-shortage-china-thailand"
      },
      "category": "commercial",
      "keywords": [],
      "publishedAt": "2026-03-16T19:10:42.000Z"
    },
    {
      "id": "g4xvk5",
      "type": "news",
      "headline": "Gridlock In The Skies: Severe Storms Halt US Flight Schedules",
      "blurb": "Severe weather across several regions of the US causes disrupted air travel, forcing multiple major airports to slow or pause flight operations.",
      "takeaway": "Commercial aviation dynamics shape travel industry.",
      "source": {
        "name": "Simple Flying",
        "url": "https://simpleflying.com/gridlock-skies-severe-storms-halt-us-flight-schedules/"
      },
      "category": "commercial",
      "keywords": [
        "airport"
      ],
      "publishedAt": "2026-03-16T19:03:51.000Z"
    },
    {
      "id": "h6jccl",
      "type": "news",
      "headline": "5 Airlines' Economy Seats With The World's Best Recline In 2026",
      "blurb": "These airlines' economy seats are among the world's best for a variety of reasons.",
      "takeaway": "Commercial aviation dynamics shape travel industry.",
      "source": {
        "name": "Simple Flying",
        "url": "https://simpleflying.com/5-airlines-economy-seats-worlds-best-recline-2026/"
      },
      "category": "commercial",
      "keywords": [
        "airline"
      ],
      "publishedAt": "2026-03-16T19:00:17.000Z"
    },
    {
      "id": "yt-faa-aviation-safety-oshkosh",
      "type": "video",
      "headline": "FAA Aviation Safety at Oshkosh",
      "blurb": "Go behind the scenes at EAA AirVenture with the FAA's Aviation Safety organization. Meet the people who help ensure safety at this event and provide essential information resources to the general aviation community.",
      "takeaway": "Safety implications warrant industry attention.",
      "source": {
        "name": "Federal Aviation Administration (YouTube)",
        "url": "https://www.youtube.com/watch?v=hlAFUO1S0Xs"
      },
      "category": "safety",
      "keywords": [
        "regulation",
        "hypoxia",
        "accident",
        "certification",
        "medicine",
        "forum"
      ],
      "publishedAt": "2026-03-16T23:36:53.600Z",
      "videoContent": true,
      "duration": "16:49"
    },
    {
      "id": "v3tfok",
      "type": "news",
      "headline": "SPARCS CubeSat ‘First Light’ Images",
      "blurb": "Description This pair of images shows stars observed by the SPARCS (Star-Planet Activity Research CubeSat) space telescope simultaneously in the near-ultraviolet, left, and far-ultraviolet, right. These observations were recorded on Feb. 6, 2026, three weeks after the cube satellite, or CubeSat, ...",
      "takeaway": "Aerospace developments expand industry horizons.",
      "source": {
        "name": "NASA",
        "url": "https://science.nasa.gov/photojournal/sparcs-cubesat-first-light-images/"
      },
      "category": "aerospace",
      "keywords": [
        "spacex",
        "space"
      ],
      "publishedAt": "2026-03-16T18:52:50.000Z"
    },
    {
      "id": "t4fgyk",
      "type": "news",
      "headline": "To Protect Artemis II Astronauts, NASA Experts Keep Eyes on Sun",
      "blurb": "As four astronauts travel around the Moon on NASA’s Artemis II mission, they will venture beyond Earth’s protective magnetic field. The crew’s spacecraft, Orion, will carry and protect them as they journey into deep space and serves as the main protection against the Sun’s intense power. During t...",
      "takeaway": "Aerospace developments expand industry horizons.",
      "source": {
        "name": "NASA",
        "url": "https://science.nasa.gov/missions/artemis/artemis-2/to-protect-artemis-ii-astronauts-nasa-experts-keep-eyes-on-sun/"
      },
      "category": "aerospace",
      "keywords": [
        "nasa",
        "space"
      ],
      "publishedAt": "2026-03-16T18:42:13.000Z"
    },
    {
      "id": "bzwhhu",
      "type": "news",
      "headline": "6 Airbus A380 Airlines Have Pulled Out Of Melbourne — Is The Superjumbo Dead?",
      "blurb": "The Airbus A380 once dominated Melbourne Airport, but now only two airlines remain, raising questions about the future of the superjumbo.",
      "takeaway": "Airbus activity reflects European aerospace trends.",
      "source": {
        "name": "Simple Flying",
        "url": "https://simpleflying.com/6-a380-airlines-pulled-out-of-melbourne/"
      },
      "category": "commercial",
      "keywords": [
        "airbus",
        "airline",
        "airport"
      ],
      "publishedAt": "2026-03-16T18:36:14.000Z"
    },
    {
      "id": "c7028t",
      "type": "news",
      "headline": "How The F-22 Raptor Stacks Up Against The Chengdu J-20 In 2026",
      "blurb": "The F-22 and J-20 are two flagship fighter jets built for different missions with most their true capabilities classified.",
      "takeaway": "Commercial aviation dynamics shape travel industry.",
      "source": {
        "name": "Simple Flying",
        "url": "https://simpleflying.com/how-f-22-raptor-stacks-up-chengdu-j-20-2026/"
      },
      "category": "commercial",
      "keywords": [],
      "publishedAt": "2026-03-16T18:00:17.000Z"
    },
    {
      "id": "mdpi-future-transportation-environmentally-sustainable-aviation-by-calvet-l",
      "type": "curated",
      "headline": "Towards Environmentally Sustainable Aviation: A Review on Operational Optimization",
      "blurb": "Growing air traffic is straining airports and airspace while raising environmental concerns, and demand is only expected to increase. This paper reviews how advanced technologies and methods can expand capacity and improve efficiency across airline, airport, and flight operations. It also highlights emerging trends and gaps for future research in sustainable aviation.",
      "takeaway": "Sustainable aviation technology gains momentum.",
      "source": {
        "name": "MDPI",
        "url": "https://www.mdpi.com/2673-7590/4/2/25?utm_campaign=20260312_papers_futuretransp&utm_medium=email&utm_source=newsletter"
      },
      "category": "commercial",
      "keywords": [
        "aviation; optimization; operations research; sustainability; environmental impacts"
      ],
      "publishedAt": "2026-03-16T23:36:53.600Z"
    },
    {
      "id": "nfs4ng",
      "type": "news",
      "headline": "Safran Arrius turbine engine chosen for new GrandCabri G5 helicopter",
      "blurb": "Safran Helicopter Engines and Helicopteres Guimbal have announced an exclusive partnership to power the new GrandCabri G5, a five-seat helicopter now under development… The post Safran Arrius turbine engine chosen for new GrandCabri G5 helicopter appeared first on AeroTime.",
      "takeaway": "Commercial aviation dynamics shape travel industry.",
      "source": {
        "name": "AeroTime Hub",
        "url": "https://www.aerotime.aero/articles/safran-arrius-grandcabri-g5-helicopter-engine"
      },
      "category": "commercial",
      "keywords": [
        "saf"
      ],
      "publishedAt": "2026-03-16T17:43:47.000Z"
    },
    {
      "id": "ni3gdw",
      "type": "news",
      "headline": "Storms, TSA Staffing Lead to Massive Delays in U.S. Air Travel",
      "blurb": "Thousands of flights have been delayed or canceled as severe weather and security staffing shortages affect major hubs.",
      "takeaway": "Industry developments to monitor closely.",
      "source": {
        "name": "AVweb",
        "url": "https://avweb.com/aviation-news/storms-tsa-staffing-delays-us-air-travel/"
      },
      "category": "general-aviation",
      "keywords": [],
      "publishedAt": "2026-03-16T17:28:55.000Z"
    },
    {
      "id": "xmd3eu",
      "type": "news",
      "headline": "Meet The New King Of Cargo: Atlas Air Orders 20 Airbus A350Fs",
      "blurb": "The airline is making a major fleet investment",
      "takeaway": "Airbus activity reflects European aerospace trends.",
      "source": {
        "name": "Simple Flying",
        "url": "https://simpleflying.com/new-king-cargo-atlas-air-20-airbus-a350f/"
      },
      "category": "commercial",
      "keywords": [
        "airbus",
        "airline"
      ],
      "publishedAt": "2026-03-16T17:00:17.000Z"
    },
    {
      "id": "nzoqq",
      "type": "news",
      "headline": "AOPA Renews Federal Appeal in Red Lake Aircraft Seizure Case",
      "blurb": "Association again asks federal officials to address impoundment following emergency landing in Minnesota.",
      "takeaway": "Industry developments to monitor closely.",
      "source": {
        "name": "AVweb",
        "url": "https://avweb.com/aviation-news/aopa/aopa-new-appeal-red-lake-aircraft-seizure/"
      },
      "category": "general-aviation",
      "keywords": [],
      "publishedAt": "2026-03-16T16:23:26.000Z"
    },
    {
      "id": "s41ujf",
      "type": "news",
      "headline": "Melagen Labs and Satlyt Announce Joint ISS Mission to Demonstrate Radiation-Resilient In-Orbit Computing and Next-Gen Shielding",
      "blurb": "NEW YORK, March 2026 — Melagen Labs and Satlyt today announced a joint technology demonstration aboard the International Space Station (ISS) through the AEGIS MISSE platform. The mission will generate […] The post Melagen Labs and Satlyt Announce Joint ISS Mission to Demonstrate Radiation-Resilie...",
      "takeaway": "Aerospace developments expand industry horizons.",
      "source": {
        "name": "SpaceNews",
        "url": "https://spacenews.com/melagen-labs-and-satlyt-announce-joint-iss-mission-to-demonstrate-radiation-resilient-in-orbit-computing-and-next-gen-shielding/"
      },
      "category": "aerospace",
      "keywords": [
        "space"
      ],
      "publishedAt": "2026-03-16T16:00:00.000Z"
    },
    {
      "id": "j1clbl",
      "type": "news",
      "headline": "Atlas Air orders 20 Airbus A350F freighters",
      "blurb": "Atlas Air Worldwide has ordered 20 Airbus A350F freighters, a deal that makes the US cargo operator the… The post Atlas Air orders 20 Airbus A350F freighters appeared first on AeroTime.",
      "takeaway": "Airbus activity reflects European aerospace trends.",
      "source": {
        "name": "AeroTime Hub",
        "url": "https://www.aerotime.aero/articles/atlas-air-orders-20-airbus-a350f-freighters"
      },
      "category": "commercial",
      "keywords": [
        "airbus"
      ],
      "publishedAt": "2026-03-16T15:49:21.000Z"
    },
    {
      "id": "butr0a",
      "type": "news",
      "headline": "Anguilla Air Services provides rare chance to fly Trislander",
      "blurb": "On a good day, one can see a lot of the neighboring islands that surround Sint Maarten. The jutting mountain profile of nearby Saba island, the more leisurely hills of Saint Barthelemy, and to the north, the British Overseas Territory of Anguilla. A long, thin island, Anguilla is home to some 15,...",
      "takeaway": "Commercial aviation dynamics shape travel industry.",
      "source": {
        "name": "Runway Girl Network",
        "url": "https://runwaygirlnetwork.com/2026/03/anguilla-air-services-provides-rare-chance-to-fly-trislander/"
      },
      "category": "commercial",
      "keywords": [],
      "publishedAt": "2026-03-16T15:32:56.000Z"
    },
    {
      "id": "efhciy",
      "type": "news",
      "headline": "Kepler Communications: Call for Live-Stream Payload Concepts",
      "blurb": "Kepler is issuing a call for payloads seeking persistent, real-time data streaming in Low Earth Orbit. Integration starts soon for the limited number of hosted payload slots remaining available across […] The post Kepler Communications: Call for Live-Stream Payload Concepts appeared first on Spac...",
      "takeaway": "Aerospace developments expand industry horizons.",
      "source": {
        "name": "SpaceNews",
        "url": "https://spacenews.com/kepler-communications-call-for-live-stream-payload-concepts/"
      },
      "category": "aerospace",
      "keywords": [
        "space"
      ],
      "publishedAt": "2026-03-16T15:00:00.000Z"
    },
    {
      "id": "xfczit",
      "type": "news",
      "headline": "Poll: Pentagon vs. Cruz on ROTOR Act",
      "blurb": "Was the Pentagon’s opposition justified, or was it “misinformation” as Cruz claims?",
      "takeaway": "Industry developments to monitor closely.",
      "source": {
        "name": "AVweb",
        "url": "https://avweb.com/polls-quizzes/poll-pentagon-vs-cruz-on-rotor-act/"
      },
      "category": "general-aviation",
      "keywords": [],
      "publishedAt": "2026-03-16T14:58:47.000Z"
    },
    {
      "id": "4g0ucv",
      "type": "news",
      "headline": "Cruz: Pentagon ‘Blindsided’ Effort To Advance Rotor Act",
      "blurb": "Texas senator says discussions with defense officials continue following House defeat of air safety measure.",
      "takeaway": "Safety implications warrant industry attention.",
      "source": {
        "name": "AVweb",
        "url": "https://avweb.com/aviation-news/cruz-pentagon-blindsided-rotor-act-effort/"
      },
      "category": "general-aviation",
      "keywords": [
        "saf",
        "safety"
      ],
      "publishedAt": "2026-03-16T14:51:13.000Z"
    },
    {
      "id": "12a7d1",
      "type": "news",
      "headline": "Ground stops at Atlanta and Charlotte airports as US braces for huge storms",
      "blurb": "Ground stops have been issued at Hartsfield-Jackson Atlanta International Airport (ATL) and Charlotte Douglas International Airport (CLT) as… The post Ground stops at Atlanta and Charlotte airports as US braces for huge storms appeared first on AeroTime.",
      "takeaway": "Commercial aviation dynamics shape travel industry.",
      "source": {
        "name": "AeroTime Hub",
        "url": "https://www.aerotime.aero/articles/ground-stops-atlanta-charlotte-airports-us-storms"
      },
      "category": "commercial",
      "keywords": [
        "airport"
      ],
      "publishedAt": "2026-03-16T14:44:30.000Z"
    },
    {
      "id": "mvd8mp",
      "type": "news",
      "headline": "Vertical Aerospace",
      "blurb": "At Vertical Aerospace, we are pioneering the way for electric aviation. The Valo, our eVTOL",
      "takeaway": "Urban air mobility advances toward commercial reality.",
      "source": {
        "name": "sUAS News",
        "url": "https://www.suasnews.com/2026/03/vertical-aerospace-head-of-flight-test/"
      },
      "category": "drones",
      "keywords": [
        "evtol",
        "electric",
        "space"
      ],
      "publishedAt": "2026-03-16T14:44:21.000Z"
    },
    {
      "id": "uw4cq",
      "type": "news",
      "headline": "U.S. House Unanimously Passes Congressman Fong’s ACERO Act",
      "blurb": "WASHINGTON, D.C. — Today, the U.S. House of Representatives unanimously passed Congressman Vince Fong’s (CA-20) H.R. 390: The Advanced",
      "takeaway": "Drone technology continues to reshape aviation operations.",
      "source": {
        "name": "sUAS News",
        "url": "https://www.suasnews.com/2026/03/u-s-house-unanimously-passes-congressman-fongs-acero-act/"
      },
      "category": "drones",
      "keywords": [],
      "publishedAt": "2026-03-16T14:30:20.000Z"
    },
    {
      "id": "5y271x",
      "type": "news",
      "headline": "Press Release: Starling Aerospace to unveil new seat family at AIX",
      "blurb": "Leading aircraft interior specialist, Starling Aerospace, will officially unveil a new family of bespoke aircraft seating solutions at the Aircraft Interiors Expo (AIX) in Hamburg next month. Heralding a new chapter in the 25-year-old company’s development, Starling will showcase its new seating ...",
      "takeaway": "Aerospace developments expand industry horizons.",
      "source": {
        "name": "Runway Girl Network",
        "url": "https://runwaygirlnetwork.com/2026/03/starling-aerospace-new-seat-family/"
      },
      "category": "commercial",
      "keywords": [
        "space"
      ],
      "publishedAt": "2026-03-16T14:00:11.000Z"
    },
    {
      "id": "s23rnv",
      "type": "news",
      "headline": "Celebrating 100 Years Since Goddard’s Breakthrough Moment in Modern Rocketry",
      "blurb": "From the voyages of spacecraft to the Moon and beyond, to the launches of satellites that help us navigate, communicate, and understand our planet and the universe, the use of liquid-fueled rockets has been key to humanity’s use and exploration of space. Today marks 100 years since the first succ...",
      "takeaway": "Aerospace developments expand industry horizons.",
      "source": {
        "name": "NASA",
        "url": "https://www.nasa.gov/image-article/celebrating-100-years-since-goddards-breakthrough-moment-in-modern-rocketry/"
      },
      "category": "aerospace",
      "keywords": [
        "space"
      ],
      "publishedAt": "2026-03-16T13:58:05.000Z"
    }
  ]
}